{
  "db_name": "PostgreSQL",
  "query": "\n            UPDATE core.blobs\n            SET \n                verification_status = $1,\n                last_verified_at = $2\n            WHERE id = $3\n            ",
  "describe": {
    "columns": [],
    "parameters": {
      "Left": [
        "Text",
        "Timestamptz",
        {
          "Custom": {
            "name": "ulid",
            "kind": "Simple"
          }
        }
      ]
    },
    "nullable": []
  },
  "hash": "dd7b58f87695983f0505d0fefbe5f6e5f5f809ffd0b461180a395ef4eb42b12d"
}
