{
  "db_name": "PostgreSQL",
  "query": "\n                SELECT \n                    id as \"material_id: Ulid\"\n                FROM raw.source_material_registry\n                WHERE source_identifier IN ('desktop_clipboard', 'desktop_window_manager', 'desktop_snapshot', 'desktop_monitoring')\n                AND NOT EXISTS (\n                    SELECT 1 FROM core.events \n                    WHERE source_material_id = source_material_registry.id\n                )\n                ORDER BY staged_at DESC\n                LIMIT 10\n                ",
  "describe": {
    "columns": [
      {
        "ordinal": 0,
        "name": "material_id: Ulid",
        "type_info": {
          "Custom": {
            "name": "ulid",
            "kind": "Simple"
          }
        }
      }
    ],
    "parameters": {
      "Left": []
    },
    "nullable": [
      false
    ]
  },
  "hash": "29d8181f28eef88da11bc862a4e3b9a977c171b0762a84cf70f0990ec5a07b35"
}
