{
  "$schema": "http://json-schema.org/draft-07/schema#",
  "properties": {
    "annex_key": {
      "type": [
        "string",
        "null"
      ]
    },
    "blob_id": {
      "type": [
        "string",
        "null"
      ]
    },
    "content_hash": {
      "type": "string"
    },
    "content_size": {
      "format": "uint",
      "minimum": 0.0,
      "type": "integer"
    },
    "content_type": {
      "type": "string"
    },
    "file_count": {
      "format": "uint",
      "minimum": 0.0,
      "type": [
        "integer",
        "null"
      ]
    },
    "file_paths": {
      "items": {
        "type": "string"
      },
      "type": [
        "array",
        "null"
      ]
    },
    "operation": {
      "type": "string"
    },
    "original_hash": {
      "type": [
        "string",
        "null"
      ]
    },
    "source_app": {
      "type": [
        "string",
        "null"
      ]
    },
    "text_preview": {
      "type": [
        "string",
        "null"
      ]
    },
    "window_title": {
      "type": [
        "string",
        "null"
      ]
    }
  },
  "required": [
    "content_hash",
    "content_size",
    "content_type",
    "operation"
  ],
  "title": "ClipboardCopiedPayload",
  "type": "object"
}